antback/__init__.py
antback/antback.py
antback/antreport_templ.htm
antback/cfd.py
antback/comnt.py
antback/utils.py
antback-0.0.9.dist-info/METADATA
antback-0.0.9.dist-info/WHEEL
antback-0.0.9.dist-info/RECORD
