Metadata-Version: 2.4
Name: antback
Version: 0.0.9
Summary: Antback: Lightweight Backtesting with Heavyweight Insight
Project-URL: Homepage, https://github.com/ts-kontakt/antback
Project-URL: Issues, https://github.com/ts-kontakt/antback/issues
Author-email: Tomasz Sługocki <ts.kontakt@gmail.com>
Requires-Dist: df2tables
Requires-Dist: pandas
